smart_flask_instrumentator/__init__.py
smart_flask_instrumentator-0.1.1.dist-info/LICENSE
smart_flask_instrumentator-0.1.1.dist-info/METADATA
smart_flask_instrumentator-0.1.1.dist-info/WHEEL
smart_flask_instrumentator-0.1.1.dist-info/RECORD
